README.rst
setup.py
portier/__init__.py
portier/ui.py
portier.egg-info/PKG-INFO
portier.egg-info/SOURCES.txt
portier.egg-info/dependency_links.txt
portier.egg-info/entry_points.txt
portier.egg-info/top_level.txt