Metadata-Version: 1.0
Name: portier
Version: 0.1.2
Summary: A tool to check a host address for open ports using multiple threads.
Home-page: https://cb109@bitbucket.org/cb109/portier.git
Author: Christoph Buelter
Author-email: c.buelter@arcor.de
License: UNKNOWN
Keywords: host,localhost,web,port,scanner,thread
Platform: UNKNOWN
